setup.py
zuoyeji/__init__.py
zuoyeji.egg-info/PKG-INFO
zuoyeji.egg-info/SOURCES.txt
zuoyeji.egg-info/dependency_links.txt
zuoyeji.egg-info/top_level.txt