Metadata-Version: 1.0
Name: zuoyeji
Version: 0.0.0
Summary: homework machine
Home-page: https://github.com/zhihuijin/zuoyeji
Author: UNKNOWN
Author-email: UNKNOWN
License: UNKNOWN
Platform: UNKNOWN
